toga_iOS/__init__.py
toga_iOS/app.py
toga_iOS/colors.py
toga_iOS/command.py
toga_iOS/constraints.py
toga_iOS/container.py
toga_iOS/dialogs.py
toga_iOS/factory.py
toga_iOS/fonts.py
toga_iOS/icons.py
toga_iOS/images.py
toga_iOS/paths.py
toga_iOS/screens.py
toga_iOS/statusicons.py
toga_iOS/window.py
toga_iOS/hardware/__init__.py
toga_iOS/hardware/camera.py
toga_iOS/hardware/location.py
toga_iOS/libs/__init__.py
toga_iOS/libs/av_foundation.py
toga_iOS/libs/core_graphics.py
toga_iOS/libs/core_location.py
toga_iOS/libs/core_text.py
toga_iOS/libs/foundation.py
toga_iOS/libs/mapkit.py
toga_iOS/libs/uikit.py
toga_iOS/libs/webkit.py
toga_iOS/resources/optioncontainer-tab.png
toga_iOS/resources/toga.icns
toga_iOS/widgets/__init__.py
toga_iOS/widgets/activityindicator.py
toga_iOS/widgets/base.py
toga_iOS/widgets/box.py
toga_iOS/widgets/button.py
toga_iOS/widgets/canvas.py
toga_iOS/widgets/detailedlist.py
toga_iOS/widgets/divider.py
toga_iOS/widgets/imageview.py
toga_iOS/widgets/label.py
toga_iOS/widgets/mapview.py
toga_iOS/widgets/multilinetextinput.py
toga_iOS/widgets/numberinput.py
toga_iOS/widgets/optioncontainer.py
toga_iOS/widgets/passwordinput.py
toga_iOS/widgets/progressbar.py
toga_iOS/widgets/scrollcontainer.py
toga_iOS/widgets/selection.py
toga_iOS/widgets/slider.py
toga_iOS/widgets/switch.py
toga_iOS/widgets/textinput.py
toga_iOS/widgets/webview.py
toga_ios-0.5.1.dist-info/licenses/LICENSE
toga_ios-0.5.1.dist-info/METADATA
toga_ios-0.5.1.dist-info/WHEEL
toga_ios-0.5.1.dist-info/entry_points.txt
toga_ios-0.5.1.dist-info/top_level.txt
toga_ios-0.5.1.dist-info/RECORD
